{
    "sections": {
      "hero": {
        "type": "hero"
      },
      "made-child": {
        "type": "made-child"
      },
      "offer": {
        "type": "offer"
      },
      "works": {
        "type": "works"
      },
      "testimonials_featured": {
        "type": "testimonials-featured"
      },
      "footer_cta": {
        "type": "footer-cta"
      }
    },
    "order": [
      "hero",
      "made-child",
      "offer",
      "works",
      "testimonials_featured",
      "footer_cta"
    ]
  }
